odoo/addons/project_members/README.rst
odoo/addons/project_members/__init__.py
odoo/addons/project_members/__manifest__.py
odoo/addons/project_members/models/__init__.py
odoo/addons/project_members/models/project.py
odoo/addons/project_members/readme/CONTRIBUTORS.rst
odoo/addons/project_members/readme/DESCRIPTION.rst
odoo/addons/project_members/readme/USAGE.rst
odoo/addons/project_members/static/description/icon.png
odoo/addons/project_members/static/description/index.html
odoo/addons/project_members/views/project.xml
odoo13_addon_project_members-13.0.1.0.0.dist-info/METADATA
odoo13_addon_project_members-13.0.1.0.0.dist-info/WHEEL
odoo13_addon_project_members-13.0.1.0.0.dist-info/top_level.txt
odoo13_addon_project_members-13.0.1.0.0.dist-info/RECORD
